resport/__init__.py
resport/__main__.py
resport-0.1.2.dist-info/entry_points.txt
resport-0.1.2.dist-info/LICENSE
resport-0.1.2.dist-info/WHEEL
resport-0.1.2.dist-info/METADATA
resport-0.1.2.dist-info/RECORD
