Metadata-Version: 2.1
Name: resport
Version: 0.1.2
Summary: resport: Research portfolio site generator.
Author-email: Alex Wolf <f.alexander.wolf@gmail.com>
Classifier: License :: OSI Approved :: MIT License
Requires-Dist: markdown
Requires-Dist: dirsync
Requires-Dist: python-markdown-math
Project-URL: Home, https://github.com/falexwolf/resport
